Metadata-Version: 1.1
Name: oauth1-py3
Version: 1.0.2
Summary: Library for OAuth version 1.0a. (Python 3)
Home-page: https://github.com/Navegg/oauth1-py3
Author: William Marquardt
Author-email: williammqt@gmail.com
License: MIT License
Platform: UNKNOWN
Classifier: Programming Language :: Python :: 3
